vidmaster/cli.py
vidmaster/clip_builder.py
vidmaster/parser.py
vidmaster/workbench.py
vidmaster/__init__.py
vidmaster-0.1.2.dist-info/DESCRIPTION.rst
vidmaster-0.1.2.dist-info/entry_points.txt
vidmaster-0.1.2.dist-info/METADATA
vidmaster-0.1.2.dist-info/metadata.json
vidmaster-0.1.2.dist-info/RECORD
vidmaster-0.1.2.dist-info/top_level.txt
vidmaster-0.1.2.dist-info/WHEEL
