Metadata-Version: 2.0
Name: vidmaster
Version: 0.1.2
Summary: Automated video compositions
Home-page: https://github.com/rmed/vidmaster
Author: Rafael Medina García
Author-email: rafamedgar@gmail.com
License: MIT
Keywords: gul vidmaster gultalks video edition composition automated
Platform: UNKNOWN
Classifier: Development Status :: 5 - Production/Stable
Classifier: Environment :: Console
Classifier: Topic :: Multimedia
Classifier: Topic :: Utilities
Classifier: License :: OSI Approved :: MIT License
Classifier: Programming Language :: Python :: 2
Classifier: Programming Language :: Python :: 2.7
Classifier: Programming Language :: Python :: 3
Classifier: Programming Language :: Python :: 3.4
Requires-Dist: moviepy (==0.2.2.11)
